overture2hdx/__init__.py
overture2hdx/__version__.py
overture2hdx/app.py
overture2hdx-0.1.1.dist-info/WHEEL
overture2hdx-0.1.1.dist-info/METADATA
overture2hdx-0.1.1.dist-info/licenses/LICENSE
overture2hdx-0.1.1.dist-info/RECORD
