Metadata-Version: 2.1
Name: overture2hdx
Version: 0.1.1
Summary: Lib to convert Overture data in GIS formats and upload it to HDX 
License: GPL-3.0-only
Keywords: overture,humanitarian,duckdb,hdx
Author-email: Kshitij Raj Sharma <skshitizraj@gmail.com>
Requires-Python: >=3.9,<4.0
Classifier: Programming Language :: Python :: 3
Classifier: Programming Language :: Python :: 3.10
Classifier: Programming Language :: Python :: 3.11
Classifier: Programming Language :: Python :: 3.9
Classifier: Topic :: Scientific/Engineering :: GIS
Classifier: Topic :: Utilities
Requires-Dist: duckdb>=1.1.0
Requires-Dist: geopandas>=1.0.1
Requires-Dist: hdx-python-api>=6.3.4
Requires-Dist: psutil<8.0.0,>=7.0.0
Requires-Dist: requests>=2.32.3
Requires-Dist: tqdm<5.0.0,>=4.67.1
Provides-Extra: docs
Requires-Dist: mkdocs>=1.5.3; extra == "docs"
Requires-Dist: mkdocs-material>=9.4.2; extra == "docs"
Requires-Dist: mkdocstrings-python>=1.7.0; extra == "docs"
Requires-Dist: mkdocs-exclude>=1.0.2; extra == "docs"
Provides-Extra: test
Requires-Dist: pytest>=7.4.2; extra == "test"
Requires-Dist: pytest-mock>=3.14.0; extra == "test"
Requires-Dist: coverage>=7.6.1; extra == "test"
Requires-Dist: coverage-badge>=1.1.2; extra == "test"
Project-URL: documentation, https://github.com/kshitijrajsharma/overture2hdx
Project-URL: homepage, https://github.com/kshitijrajsharma/overture2hdx
Project-URL: repository, https://github.com/kshitijrajsharma/overture2hdx
